AUTHORS.rst
CHANGES.rst
CONTRIBUTING.rst
LICENSE.txt
MANIFEST.in
README.rst
doc-requirements.txt
setup.cfg
setup.py
docs/advanced.rst
docs/index.rst
docs/reference.rst
docs/usage.rst
rca_django_simple_history.egg-info/PKG-INFO
rca_django_simple_history.egg-info/SOURCES.txt
rca_django_simple_history.egg-info/dependency_links.txt
rca_django_simple_history.egg-info/top_level.txt
simple_history/__init__.py
simple_history/admin.py
simple_history/exceptions.py
simple_history/manager.py
simple_history/middleware.py
simple_history/models.py
simple_history/utils.py
simple_history/locale/pl/LC_MESSAGES/django.mo
simple_history/locale/pl/LC_MESSAGES/django.po
simple_history/locale/pt_BR/LC_MESSAGES/django.mo
simple_history/locale/pt_BR/LC_MESSAGES/django.po
simple_history/management/__init__.py
simple_history/management/commands/__init__.py
simple_history/management/commands/_populate_utils.py
simple_history/management/commands/populate_history.py
simple_history/templates/simple_history/_object_history_list.html
simple_history/templates/simple_history/object_history.html
simple_history/templates/simple_history/object_history_form.html
simple_history/templates/simple_history/submit_line.html
simple_history/templatetags/__init__.py
simple_history/templatetags/getattributes.py
simple_history/templatetags/simple_history_admin_list.py
simple_history/templatetags/simple_history_compat.py